package/__init__.py
k0d_expert-0.0.1.dist-info/LICENSE
k0d_expert-0.0.1.dist-info/WHEEL
k0d_expert-0.0.1.dist-info/METADATA
k0d_expert-0.0.1.dist-info/RECORD
